sphinxcontrib_log_cabinet-1.0.1-py3.7-nspkg.pth
sphinxcontrib/log_cabinet.py
sphinxcontrib_log_cabinet-1.0.1.dist-info/LICENSE.rst
sphinxcontrib_log_cabinet-1.0.1.dist-info/METADATA
sphinxcontrib_log_cabinet-1.0.1.dist-info/WHEEL
sphinxcontrib_log_cabinet-1.0.1.dist-info/namespace_packages.txt
sphinxcontrib_log_cabinet-1.0.1.dist-info/top_level.txt
sphinxcontrib_log_cabinet-1.0.1.dist-info/RECORD
